demo/__init__.py
demo/main.py
ttviewer-0.0.1.dist-info/METADATA
ttviewer-0.0.1.dist-info/WHEEL
ttviewer-0.0.1.dist-info/top_level.txt
ttviewer-0.0.1.dist-info/RECORD
